setup.py
Fahads_Random_Game/Fahads_Random_Game.py
Fahads_Random_Game/__init__.py
Fahads_Random_Game.egg-info/PKG-INFO
Fahads_Random_Game.egg-info/SOURCES.txt
Fahads_Random_Game.egg-info/dependency_links.txt
Fahads_Random_Game.egg-info/not-zip-safe
Fahads_Random_Game.egg-info/top_level.txt