Metadata-Version: 1.0
Name: Fahads-Random-Game
Version: 0.1
Summary: paly with your computer
Home-page: UNKNOWN
Author: UNKNOWN
Author-email: UNKNOWN
License: UNKNOWN
Platform: UNKNOWN
